{
  "schema_version": 2,
  "id": "minecraft_data_api",
  "latest_version": "1.4.1",
  "etag": "\"6a7a0e4cd5308ea78ce0a2a4104c54c7521bece9614fae510aa769b6d588133f\"",
  "releases": [
    {
      "url": "https://github.com/MCDReforged/MinecraftDataAPI/releases/tag/v1.4.1",
      "name": "MinecraftDataAPI v1.4.1",
      "tag_name": "v1.4.1",
      "created_at": "2021-08-16T17:13:30Z",
      "assets": [
        {
          "name": "MinecraftDataAPI-v1.4.1.mcdr",
          "size": 17831,
          "download_count": 3132,
          "created_at": "2021-08-16T17:14:55Z",
          "browser_download_url": "https://github.com/MCDReforged/MinecraftDataAPI/releases/download/v1.4.1/MinecraftDataAPI-v1.4.1.mcdr"
        }
      ],
      "description": "Release for MCDR 2.0",
      "prerelease": false,
      "parsed_version": "1.4.1"
    }
  ]
}